<?xml version="1.0" encoding="UTF-8"?>
<m:mets xmlns:m="http://www.loc.gov/METS/" xmlns:xlink="http://www.w3.org/1999/xlink" xmlns="http://www.w3.org/1999/xhtml" xmlns:md="http://www.loc.gov/mods/v3" OBJID="manus:592">
  <m:metsHdr>
    <m:agent ROLE="CREATOR">
      <m:name>dk.kb.dup.metsApi software agent using data from Manuscript
department at Royal Library, Copenhagen, DK.</m:name>
      <m:note>Software release $Id: Manus.java,v 1.19 2007/01/19 14:40:44 jac Exp $</m:note>
    </m:agent>
  </m:metsHdr>
  <m:dmdSec ID="md-root">
    <m:mdWrap MDTYPE="MODS">
      <m:xmlData>
        <md:mods>
          <md:titleInfo xml:lang="dan">
            <md:title>Dagbog XXXV</md:title>
          </md:titleInfo>
          <md:name xml:lang="dan">
            <md:partName>Jens Baggesen</md:partName>
            <md:role>
              <md:roleTerm>author</md:roleTerm>
            </md:role>
          </md:name>
          <md:language>
            <md:languageTerm type="code" authority="iso639-2b">dan</md:languageTerm>
          </md:language>
          <md:note type="presentation" xml:lang="dan">
            <div xmlns="">
              <p>Dagbog XXXV er indbundet i et papbind, der har følgende dimensioner: 20,5 x 31 cm.</p>
              <p>[Jens Baggesen: Dagbøger 1780-1825, I-XLIV (42 vol.). NKS 504 8º]</p>
            </div>
          </md:note>
          <md:relatedItem type="host">
            <md:titleInfo xml:lang="dan">
              <md:title>Center for Manuskripter &amp; Boghistorie</md:title>
            </md:titleInfo>
            <md:titleInfo xml:lang="eng">
              <md:title>Center for Manuscripts &amp; Rare Books</md:title>
            </md:titleInfo>
            <md:titleInfo xml:lang="esp">
              <md:title>Departamento de Manuscritos</md:title>
            </md:titleInfo>
            <md:identifier type="uri" xml:lang="dan">/da/kb/nb/ha/index.html</md:identifier>
            <md:identifier type="uri" xml:lang="eng">/en/kb/nb/ha/index.html</md:identifier>
          </md:relatedItem>
          <md:identifier type="signature">NKS 504, 8</md:identifier>
        </md:mods>
      </m:xmlData>
    </m:mdWrap>
  </m:dmdSec>
  <m:fileSec>
    <m:fileGrp>
      <m:file ID="file:default:592:91438">
        <m:FLocat LOCTYPE="URL" xlink:href="http://img.kb.dk/ha/manus/baggesen/dgb35/dgb35_001.jpg"/>
      </m:file>
      <m:file ID="file:default:592:91659">
        <m:FLocat LOCTYPE="URL" xlink:href="http://img.kb.dk/ha/manus/baggesen/dgb35/side2.jpg"/>
      </m:file>
      <m:file ID="file:default:592:91660">
        <m:FLocat LOCTYPE="URL" xlink:href="http://img.kb.dk/ha/manus/baggesen/dgb35/side3.jpg"/>
      </m:file>
      <m:file ID="file:default:592:91417">
        <m:FLocat LOCTYPE="URL" xlink:href="http://img.kb.dk/ha/manus/baggesen/dgb35/dgb35_002.jpg"/>
      </m:file>
      <m:file ID="file:default:592:91418">
        <m:FLocat LOCTYPE="URL" xlink:href="http://img.kb.dk/ha/manus/baggesen/dgb35/dgb35_003.jpg"/>
      </m:file>
      <m:file ID="file:default:592:91419">
        <m:FLocat LOCTYPE="URL" xlink:href="http://img.kb.dk/ha/manus/baggesen/dgb35/dgb35_004.jpg"/>
      </m:file>
      <m:file ID="file:default:592:91420">
        <m:FLocat LOCTYPE="URL" xlink:href="http://img.kb.dk/ha/manus/baggesen/dgb35/dgb35_005.jpg"/>
      </m:file>
      <m:file ID="file:default:592:91421">
        <m:FLocat LOCTYPE="URL" xlink:href="http://img.kb.dk/ha/manus/baggesen/dgb35/dgb35_006.jpg"/>
      </m:file>
      <m:file ID="file:default:592:91422">
        <m:FLocat LOCTYPE="URL" xlink:href="http://img.kb.dk/ha/manus/baggesen/dgb35/dgb35_007.jpg"/>
      </m:file>
      <m:file ID="file:default:592:91423">
        <m:FLocat LOCTYPE="URL" xlink:href="http://img.kb.dk/ha/manus/baggesen/dgb35/dgb35_008.jpg"/>
      </m:file>
      <m:file ID="file:default:592:91424">
        <m:FLocat LOCTYPE="URL" xlink:href="http://img.kb.dk/ha/manus/baggesen/dgb35/dgb35_009.jpg"/>
      </m:file>
      <m:file ID="file:default:592:91425">
        <m:FLocat LOCTYPE="URL" xlink:href="http://img.kb.dk/ha/manus/baggesen/dgb35/dgb35_010.jpg"/>
      </m:file>
      <m:file ID="file:default:592:91426">
        <m:FLocat LOCTYPE="URL" xlink:href="http://img.kb.dk/ha/manus/baggesen/dgb35/dgb35_011.jpg"/>
      </m:file>
      <m:file ID="file:default:592:91427">
        <m:FLocat LOCTYPE="URL" xlink:href="http://img.kb.dk/ha/manus/baggesen/dgb35/dgb35_012.jpg"/>
      </m:file>
      <m:file ID="file:default:592:91428">
        <m:FLocat LOCTYPE="URL" xlink:href="http://img.kb.dk/ha/manus/baggesen/dgb35/dgb35_013.jpg"/>
      </m:file>
      <m:file ID="file:default:592:91429">
        <m:FLocat LOCTYPE="URL" xlink:href="http://img.kb.dk/ha/manus/baggesen/dgb35/dgb35_014.jpg"/>
      </m:file>
      <m:file ID="file:default:592:91430">
        <m:FLocat LOCTYPE="URL" xlink:href="http://img.kb.dk/ha/manus/baggesen/dgb35/dgb35_015.jpg"/>
      </m:file>
      <m:file ID="file:default:592:91431">
        <m:FLocat LOCTYPE="URL" xlink:href="http://img.kb.dk/ha/manus/baggesen/dgb35/dgb35_016.jpg"/>
      </m:file>
      <m:file ID="file:default:592:91432">
        <m:FLocat LOCTYPE="URL" xlink:href="http://img.kb.dk/ha/manus/baggesen/dgb35/dgb35_017.jpg"/>
      </m:file>
      <m:file ID="file:default:592:91433">
        <m:FLocat LOCTYPE="URL" xlink:href="http://img.kb.dk/ha/manus/baggesen/dgb35/dgb35_018.jpg"/>
      </m:file>
      <m:file ID="file:default:592:91434">
        <m:FLocat LOCTYPE="URL" xlink:href="http://img.kb.dk/ha/manus/baggesen/dgb35/dgb35_019.jpg"/>
      </m:file>
      <m:file ID="file:default:592:91435">
        <m:FLocat LOCTYPE="URL" xlink:href="http://img.kb.dk/ha/manus/baggesen/dgb35/dgb35_020.jpg"/>
      </m:file>
      <m:file ID="file:default:592:91436">
        <m:FLocat LOCTYPE="URL" xlink:href="http://img.kb.dk/ha/manus/baggesen/dgb35/dgb35_021.jpg"/>
      </m:file>
      <m:file ID="file:default:592:91437">
        <m:FLocat LOCTYPE="URL" xlink:href="http://img.kb.dk/ha/manus/baggesen/dgb35/dgb35_022.jpg"/>
      </m:file>
    </m:fileGrp>
    <m:fileGrp>
      <m:file ID="file:variant:592:71419">
        <m:FLocat LOCTYPE="URL" xlink:href="http://img.kb.dk/ha/manus/baggesen/dgb35/dgb35_001v.jpg"/>
      </m:file>
      <m:file ID="file:variant:592:71425">
        <m:FLocat LOCTYPE="URL" xlink:href="http://img.kb.dk/ha/manus/baggesen/dgb35/dgb35_007v.jpg"/>
      </m:file>
      <m:file ID="file:variant:592:71427">
        <m:FLocat LOCTYPE="URL" xlink:href="http://img.kb.dk/ha/manus/baggesen/dgb35/dgb35_009v.jpg"/>
      </m:file>
      <m:file ID="file:variant:592:71428">
        <m:FLocat LOCTYPE="URL" xlink:href="http://img.kb.dk/ha/manus/baggesen/dgb35/dgb35_010v.jpg"/>
      </m:file>
      <m:file ID="file:variant:592:71429">
        <m:FLocat LOCTYPE="URL" xlink:href="http://img.kb.dk/ha/manus/baggesen/dgb35/dgb35_011v.jpg"/>
      </m:file>
      <m:file ID="file:variant:592:71430">
        <m:FLocat LOCTYPE="URL" xlink:href="http://img.kb.dk/ha/manus/baggesen/dgb35/dgb35_012v.jpg"/>
      </m:file>
      <m:file ID="file:variant:592:71431">
        <m:FLocat LOCTYPE="URL" xlink:href="http://img.kb.dk/ha/manus/baggesen/dgb35/dgb35_013v.jpg"/>
      </m:file>
      <m:file ID="file:variant:592:71432">
        <m:FLocat LOCTYPE="URL" xlink:href="http://img.kb.dk/ha/manus/baggesen/dgb35/dgb35_014v.jpg"/>
      </m:file>
      <m:file ID="file:variant:592:71433">
        <m:FLocat LOCTYPE="URL" xlink:href="http://img.kb.dk/ha/manus/baggesen/dgb35/dgb35_015v.jpg"/>
      </m:file>
      <m:file ID="file:variant:592:71434">
        <m:FLocat LOCTYPE="URL" xlink:href="http://img.kb.dk/ha/manus/baggesen/dgb35/dgb35_016v.jpg"/>
      </m:file>
      <m:file ID="file:variant:592:71435">
        <m:FLocat LOCTYPE="URL" xlink:href="http://img.kb.dk/ha/manus/baggesen/dgb35/dgb35_017v.jpg"/>
      </m:file>
      <m:file ID="file:variant:592:71661">
        <m:FLocat LOCTYPE="URL" xlink:href="http://img.kb.dk/ha/manus/baggesen/dgb35/side2v.jpg"/>
      </m:file>
      <m:file ID="file:variant:592:71436">
        <m:FLocat LOCTYPE="URL" xlink:href="http://img.kb.dk/ha/manus/baggesen/dgb35/dgb35_018v.jpg"/>
      </m:file>
      <m:file ID="file:variant:592:71437">
        <m:FLocat LOCTYPE="URL" xlink:href="http://img.kb.dk/ha/manus/baggesen/dgb35/dgb35_019v.jpg"/>
      </m:file>
      <m:file ID="file:variant:592:71438">
        <m:FLocat LOCTYPE="URL" xlink:href="http://img.kb.dk/ha/manus/baggesen/dgb35/dgb35_020v.jpg"/>
      </m:file>
      <m:file ID="file:variant:592:71439">
        <m:FLocat LOCTYPE="URL" xlink:href="http://img.kb.dk/ha/manus/baggesen/dgb35/dgb35_021v.jpg"/>
      </m:file>
      <m:file ID="file:variant:592:71440">
        <m:FLocat LOCTYPE="URL" xlink:href="http://img.kb.dk/ha/manus/baggesen/dgb35/dgb35_022v.jpg"/>
      </m:file>
      <m:file ID="file:variant:592:71662">
        <m:FLocat LOCTYPE="URL" xlink:href="http://img.kb.dk/ha/manus/baggesen/dgb35/side3v.jpg"/>
      </m:file>
      <m:file ID="file:variant:592:71420">
        <m:FLocat LOCTYPE="URL" xlink:href="http://img.kb.dk/ha/manus/baggesen/dgb35/dgb35_002v.jpg"/>
      </m:file>
      <m:file ID="file:variant:592:71421">
        <m:FLocat LOCTYPE="URL" xlink:href="http://img.kb.dk/ha/manus/baggesen/dgb35/dgb35_003v.jpg"/>
      </m:file>
      <m:file ID="file:variant:592:71422">
        <m:FLocat LOCTYPE="URL" xlink:href="http://img.kb.dk/ha/manus/baggesen/dgb35/dgb35_004v.jpg"/>
      </m:file>
      <m:file ID="file:variant:592:71423">
        <m:FLocat LOCTYPE="URL" xlink:href="http://img.kb.dk/ha/manus/baggesen/dgb35/dgb35_005v.jpg"/>
      </m:file>
      <m:file ID="file:variant:592:71424">
        <m:FLocat LOCTYPE="URL" xlink:href="http://img.kb.dk/ha/manus/baggesen/dgb35/dgb35_006v.jpg"/>
      </m:file>
      <m:file ID="file:variant:592:71426">
        <m:FLocat LOCTYPE="URL" xlink:href="http://img.kb.dk/ha/manus/baggesen/dgb35/dgb35_008v.jpg"/>
      </m:file>
    </m:fileGrp>
  </m:fileSec>
  <m:structMap type="physical">
    <m:div ID="manus:592:physical:root" DMDID="md-root">
      <m:div ID="manus:592:div:physical:91438" xml:lang="dan" ORDERLABEL="1" LABEL="Forside">
        <m:fptr FILEID="file:default:592:91438"/>
      </m:div>
      <m:div ID="manus:592:div:physical:91659" xml:lang="dan" ORDERLABEL="2">
        <m:fptr FILEID="file:default:592:91659"/>
      </m:div>
      <m:div ID="manus:592:div:physical:91660" xml:lang="dan" ORDERLABEL="3" LABEL="Paris 1.1.1803">
        <m:fptr FILEID="file:default:592:91660"/>
      </m:div>
      <m:div ID="manus:592:div:physical:91417" xml:lang="dan" ORDERLABEL="4" LABEL="Februar 1803">
        <m:fptr FILEID="file:default:592:91417"/>
      </m:div>
      <m:div ID="manus:592:div:physical:91418" xml:lang="dan" ORDERLABEL="5">
        <m:fptr FILEID="file:default:592:91418"/>
      </m:div>
      <m:div ID="manus:592:div:physical:91419" xml:lang="dan" ORDERLABEL="6">
        <m:fptr FILEID="file:default:592:91419"/>
      </m:div>
      <m:div ID="manus:592:div:physical:91420" xml:lang="dan" ORDERLABEL="7">
        <m:fptr FILEID="file:default:592:91420"/>
      </m:div>
      <m:div ID="manus:592:div:physical:91421" xml:lang="dan" ORDERLABEL="8" LABEL="Paris 15.2.1803">
        <m:fptr FILEID="file:default:592:91421"/>
      </m:div>
      <m:div ID="manus:592:div:physical:91422" xml:lang="dan" ORDERLABEL="9">
        <m:fptr FILEID="file:default:592:91422"/>
      </m:div>
      <m:div ID="manus:592:div:physical:91423" xml:lang="dan" ORDERLABEL="10">
        <m:fptr FILEID="file:default:592:91423"/>
      </m:div>
      <m:div ID="manus:592:div:physical:91424" xml:lang="dan" ORDERLABEL="11">
        <m:fptr FILEID="file:default:592:91424"/>
      </m:div>
      <m:div ID="manus:592:div:physical:91425" xml:lang="dan" ORDERLABEL="12">
        <m:fptr FILEID="file:default:592:91425"/>
      </m:div>
      <m:div ID="manus:592:div:physical:91426" xml:lang="dan" ORDERLABEL="13">
        <m:fptr FILEID="file:default:592:91426"/>
      </m:div>
      <m:div ID="manus:592:div:physical:91427" xml:lang="dan" ORDERLABEL="14">
        <m:fptr FILEID="file:default:592:91427"/>
      </m:div>
      <m:div ID="manus:592:div:physical:91428" xml:lang="dan" ORDERLABEL="15">
        <m:fptr FILEID="file:default:592:91428"/>
      </m:div>
      <m:div ID="manus:592:div:physical:91429" xml:lang="dan" ORDERLABEL="16">
        <m:fptr FILEID="file:default:592:91429"/>
      </m:div>
      <m:div ID="manus:592:div:physical:91430" xml:lang="dan" ORDERLABEL="17" LABEL="Marts 1803">
        <m:fptr FILEID="file:default:592:91430"/>
      </m:div>
      <m:div ID="manus:592:div:physical:91431" xml:lang="dan" ORDERLABEL="18">
        <m:fptr FILEID="file:default:592:91431"/>
      </m:div>
      <m:div ID="manus:592:div:physical:91432" xml:lang="dan" ORDERLABEL="19">
        <m:fptr FILEID="file:default:592:91432"/>
      </m:div>
      <m:div ID="manus:592:div:physical:91433" xml:lang="dan" ORDERLABEL="20" LABEL="April 1803">
        <m:fptr FILEID="file:default:592:91433"/>
      </m:div>
      <m:div ID="manus:592:div:physical:91434" xml:lang="dan" ORDERLABEL="21" LABEL="Juni 1803">
        <m:fptr FILEID="file:default:592:91434"/>
      </m:div>
      <m:div ID="manus:592:div:physical:91435" xml:lang="dan" ORDERLABEL="22" LABEL="November 1803">
        <m:fptr FILEID="file:default:592:91435"/>
      </m:div>
      <m:div ID="manus:592:div:physical:91436" xml:lang="dan" ORDERLABEL="23" LABEL="Paris 1.1.1804">
        <m:fptr FILEID="file:default:592:91436"/>
      </m:div>
      <m:div ID="manus:592:div:physical:91437" xml:lang="dan" ORDERLABEL="24" LABEL="Paris 5.1.1804">
        <m:fptr FILEID="file:default:592:91437"/>
      </m:div>
    </m:div>
  </m:structMap>
  <m:structMap type="variant">
    <m:div ID="manus:592:div:variant:71419" ORDERLABEL="1">
      <m:fptr FILEID="file:variant:592:71419"/>
    </m:div>
    <m:div ID="manus:592:div:variant:71425" ORDERLABEL="9">
      <m:fptr FILEID="file:variant:592:71425"/>
    </m:div>
    <m:div ID="manus:592:div:variant:71427" ORDERLABEL="11">
      <m:fptr FILEID="file:variant:592:71427"/>
    </m:div>
    <m:div ID="manus:592:div:variant:71428" ORDERLABEL="12">
      <m:fptr FILEID="file:variant:592:71428"/>
    </m:div>
    <m:div ID="manus:592:div:variant:71429" ORDERLABEL="13">
      <m:fptr FILEID="file:variant:592:71429"/>
    </m:div>
    <m:div ID="manus:592:div:variant:71430" ORDERLABEL="14">
      <m:fptr FILEID="file:variant:592:71430"/>
    </m:div>
    <m:div ID="manus:592:div:variant:71431" ORDERLABEL="15">
      <m:fptr FILEID="file:variant:592:71431"/>
    </m:div>
    <m:div ID="manus:592:div:variant:71432" ORDERLABEL="16">
      <m:fptr FILEID="file:variant:592:71432"/>
    </m:div>
    <m:div ID="manus:592:div:variant:71433" ORDERLABEL="17">
      <m:fptr FILEID="file:variant:592:71433"/>
    </m:div>
    <m:div ID="manus:592:div:variant:71434" ORDERLABEL="18">
      <m:fptr FILEID="file:variant:592:71434"/>
    </m:div>
    <m:div ID="manus:592:div:variant:71435" ORDERLABEL="19">
      <m:fptr FILEID="file:variant:592:71435"/>
    </m:div>
    <m:div ID="manus:592:div:variant:71661" ORDERLABEL="2">
      <m:fptr FILEID="file:variant:592:71661"/>
    </m:div>
    <m:div ID="manus:592:div:variant:71436" ORDERLABEL="20">
      <m:fptr FILEID="file:variant:592:71436"/>
    </m:div>
    <m:div ID="manus:592:div:variant:71437" ORDERLABEL="21">
      <m:fptr FILEID="file:variant:592:71437"/>
    </m:div>
    <m:div ID="manus:592:div:variant:71438" ORDERLABEL="22">
      <m:fptr FILEID="file:variant:592:71438"/>
    </m:div>
    <m:div ID="manus:592:div:variant:71439" ORDERLABEL="23">
      <m:fptr FILEID="file:variant:592:71439"/>
    </m:div>
    <m:div ID="manus:592:div:variant:71440" ORDERLABEL="24">
      <m:fptr FILEID="file:variant:592:71440"/>
    </m:div>
    <m:div ID="manus:592:div:variant:71662" ORDERLABEL="3">
      <m:fptr FILEID="file:variant:592:71662"/>
    </m:div>
    <m:div ID="manus:592:div:variant:71420" ORDERLABEL="4">
      <m:fptr FILEID="file:variant:592:71420"/>
    </m:div>
    <m:div ID="manus:592:div:variant:71421" ORDERLABEL="5">
      <m:fptr FILEID="file:variant:592:71421"/>
    </m:div>
    <m:div ID="manus:592:div:variant:71422" ORDERLABEL="6">
      <m:fptr FILEID="file:variant:592:71422"/>
    </m:div>
    <m:div ID="manus:592:div:variant:71423" ORDERLABEL="7">
      <m:fptr FILEID="file:variant:592:71423"/>
    </m:div>
    <m:div ID="manus:592:div:variant:71424" ORDERLABEL="8">
      <m:fptr FILEID="file:variant:592:71424"/>
    </m:div>
    <m:div ID="manus:592:div:variant:71426" ORDERLABEL="10">
      <m:fptr FILEID="file:variant:592:71426"/>
    </m:div>
  </m:structMap>
  <m:structLink>
    <m:smLink xml:lang="dan" xlink:title="Større billede" xlink:from="manus:592:div:physical:91438" xlink:to="manus:592:div:variant:71419"/>
    <m:smLink xml:lang="dan" xlink:title="Større billede" xlink:from="manus:592:div:physical:91659" xlink:to="manus:592:div:variant:71661"/>
    <m:smLink xml:lang="dan" xlink:title="Større billede" xlink:from="manus:592:div:physical:91660" xlink:to="manus:592:div:variant:71662"/>
    <m:smLink xml:lang="dan" xlink:title="Større billede" xlink:from="manus:592:div:physical:91417" xlink:to="manus:592:div:variant:71420"/>
    <m:smLink xml:lang="dan" xlink:title="Større billede" xlink:from="manus:592:div:physical:91418" xlink:to="manus:592:div:variant:71421"/>
    <m:smLink xml:lang="dan" xlink:title="Større billede" xlink:from="manus:592:div:physical:91419" xlink:to="manus:592:div:variant:71422"/>
    <m:smLink xml:lang="dan" xlink:title="Større billede" xlink:from="manus:592:div:physical:91420" xlink:to="manus:592:div:variant:71423"/>
    <m:smLink xml:lang="dan" xlink:title="Større billede" xlink:from="manus:592:div:physical:91421" xlink:to="manus:592:div:variant:71424"/>
    <m:smLink xml:lang="dan" xlink:title="Større billede" xlink:from="manus:592:div:physical:91422" xlink:to="manus:592:div:variant:71425"/>
    <m:smLink xml:lang="dan" xlink:title="Større billede" xlink:from="manus:592:div:physical:91423" xlink:to="manus:592:div:variant:71426"/>
    <m:smLink xml:lang="dan" xlink:title="Større billede" xlink:from="manus:592:div:physical:91424" xlink:to="manus:592:div:variant:71427"/>
    <m:smLink xml:lang="dan" xlink:title="Større billede" xlink:from="manus:592:div:physical:91425" xlink:to="manus:592:div:variant:71428"/>
    <m:smLink xml:lang="dan" xlink:title="Større billede" xlink:from="manus:592:div:physical:91426" xlink:to="manus:592:div:variant:71429"/>
    <m:smLink xml:lang="dan" xlink:title="Større billede" xlink:from="manus:592:div:physical:91427" xlink:to="manus:592:div:variant:71430"/>
    <m:smLink xml:lang="dan" xlink:title="Større billede" xlink:from="manus:592:div:physical:91428" xlink:to="manus:592:div:variant:71431"/>
    <m:smLink xml:lang="dan" xlink:title="Større billede" xlink:from="manus:592:div:physical:91429" xlink:to="manus:592:div:variant:71432"/>
    <m:smLink xml:lang="dan" xlink:title="Større billede" xlink:from="manus:592:div:physical:91430" xlink:to="manus:592:div:variant:71433"/>
    <m:smLink xml:lang="dan" xlink:title="Større billede" xlink:from="manus:592:div:physical:91431" xlink:to="manus:592:div:variant:71434"/>
    <m:smLink xml:lang="dan" xlink:title="Større billede" xlink:from="manus:592:div:physical:91432" xlink:to="manus:592:div:variant:71435"/>
    <m:smLink xml:lang="dan" xlink:title="Større billede" xlink:from="manus:592:div:physical:91433" xlink:to="manus:592:div:variant:71436"/>
    <m:smLink xml:lang="dan" xlink:title="Større billede" xlink:from="manus:592:div:physical:91434" xlink:to="manus:592:div:variant:71437"/>
    <m:smLink xml:lang="dan" xlink:title="Større billede" xlink:from="manus:592:div:physical:91435" xlink:to="manus:592:div:variant:71438"/>
    <m:smLink xml:lang="dan" xlink:title="Større billede" xlink:from="manus:592:div:physical:91436" xlink:to="manus:592:div:variant:71439"/>
    <m:smLink xml:lang="dan" xlink:title="Større billede" xlink:from="manus:592:div:physical:91437" xlink:to="manus:592:div:variant:71440"/>
  </m:structLink>
</m:mets>
