<?xml version="1.0" encoding="UTF-8"?>
<m:mets xmlns:m="http://www.loc.gov/METS/" xmlns:xlink="http://www.w3.org/1999/xlink" xmlns:md="http://www.loc.gov/mods/v3" xmlns="http://www.w3.org/1999/xhtml" OBJID="musman:13">
  <m:dmdSec ID="md-root">
    <m:mdWrap MDTYPE="MODS">
      <m:xmlData>
        <md:mods>
          <md:titleInfo xml:lang="dan">
            <md:title>Cantate ved Frederik 7.'s Bisættelse, op. 64b</md:title>
          </md:titleInfo>
          <md:originInfo>
            <md:dateIssued>1863</md:dateIssued>
          </md:originInfo>
          <md:note type="presentation" xml:lang="dan">
            <div xmlns="">Den 13. december 1863, kun knapt en måned efter Kongens død, havde Hartmann færdigkomponeret sørgekantaten til Frederik 7.'s bisættelse med tekst af H.P. Holst. Bisættelsen fandt sted i Roskilde Domkirke d. 19. december 1863, og Studenter-Sangforeningen samt Det Kongelige Kapel og solister fra Det Kongelige Teater stod for fremførelsen. Ifølge Hartmann selv gjorde den &quot;... en Virkning, som aldrig gjennem Sang er opnaaet i Roeskilde Domkirke før...&quot;.<br/><br/><a href="http://www.kb.dk/elib/noder/hartmann/worktexts/#13">English version</a></div>
          </md:note>
          <md:note type="caption" xml:lang="dan">
            <div xmlns=""><i>Cantate ved Frederik den Syvendes Bisættelse..., op. 64b</i><br/> Datering: 13.12. 1863<br/> 1 bd. 74 s. 34,1 x 28,7</div>
          </md:note>
          <md:relatedItem type="host">
            <md:titleInfo xml:lang="dan">
              <md:title>Musikafdelingen</md:title>
            </md:titleInfo>
            <md:identifier type="uri" xml:lang="dan">http://www.kb.dk/musik</md:identifier>
          </md:relatedItem>
          <md:identifier type="signature">Hartmanns samling</md:identifier>
          <md:identifier type="thumb">http://img.kb.dk/ma/musman/nyhartmann/forsider/fre70001.jpg</md:identifier>
        </md:mods>
      </m:xmlData>
    </m:mdWrap>
  </m:dmdSec>
  <m:fileSec>
    <m:fileGrp>
      <m:file ID="file:default:13:0">
        <m:FLocat LOCTYPE="URL" xlink:href="http://img.kb.dk/ma/musman/nyhartmann/fre7/fre70000.djvu"/>
      </m:file>
      <m:file ID="file:default:13:1">
        <m:FLocat LOCTYPE="URL" xlink:href="http://img.kb.dk/ma/musman/nyhartmann/fre7/fre70001.djvu"/>
      </m:file>
      <m:file ID="file:default:13:2">
        <m:FLocat LOCTYPE="URL" xlink:href="http://img.kb.dk/ma/musman/nyhartmann/fre7/fre70002.djvu"/>
      </m:file>
      <m:file ID="file:default:13:3">
        <m:FLocat LOCTYPE="URL" xlink:href="http://img.kb.dk/ma/musman/nyhartmann/fre7/fre70003.djvu"/>
      </m:file>
      <m:file ID="file:default:13:4">
        <m:FLocat LOCTYPE="URL" xlink:href="http://img.kb.dk/ma/musman/nyhartmann/fre7/fre70004.djvu"/>
      </m:file>
      <m:file ID="file:default:13:5">
        <m:FLocat LOCTYPE="URL" xlink:href="http://img.kb.dk/ma/musman/nyhartmann/fre7/fre70005.djvu"/>
      </m:file>
      <m:file ID="file:default:13:6">
        <m:FLocat LOCTYPE="URL" xlink:href="http://img.kb.dk/ma/musman/nyhartmann/fre7/fre70006.djvu"/>
      </m:file>
      <m:file ID="file:default:13:7">
        <m:FLocat LOCTYPE="URL" xlink:href="http://img.kb.dk/ma/musman/nyhartmann/fre7/fre70007.djvu"/>
      </m:file>
      <m:file ID="file:default:13:8">
        <m:FLocat LOCTYPE="URL" xlink:href="http://img.kb.dk/ma/musman/nyhartmann/fre7/fre70008.djvu"/>
      </m:file>
      <m:file ID="file:default:13:9">
        <m:FLocat LOCTYPE="URL" xlink:href="http://img.kb.dk/ma/musman/nyhartmann/fre7/fre70009.djvu"/>
      </m:file>
      <m:file ID="file:default:13:10">
        <m:FLocat LOCTYPE="URL" xlink:href="http://img.kb.dk/ma/musman/nyhartmann/fre7/fre70010.djvu"/>
      </m:file>
      <m:file ID="file:default:13:11">
        <m:FLocat LOCTYPE="URL" xlink:href="http://img.kb.dk/ma/musman/nyhartmann/fre7/fre70011.djvu"/>
      </m:file>
      <m:file ID="file:default:13:12">
        <m:FLocat LOCTYPE="URL" xlink:href="http://img.kb.dk/ma/musman/nyhartmann/fre7/fre70012.djvu"/>
      </m:file>
      <m:file ID="file:default:13:13">
        <m:FLocat LOCTYPE="URL" xlink:href="http://img.kb.dk/ma/musman/nyhartmann/fre7/fre70013.djvu"/>
      </m:file>
      <m:file ID="file:default:13:14">
        <m:FLocat LOCTYPE="URL" xlink:href="http://img.kb.dk/ma/musman/nyhartmann/fre7/fre70014.djvu"/>
      </m:file>
      <m:file ID="file:default:13:15">
        <m:FLocat LOCTYPE="URL" xlink:href="http://img.kb.dk/ma/musman/nyhartmann/fre7/fre70015.djvu"/>
      </m:file>
      <m:file ID="file:default:13:16">
        <m:FLocat LOCTYPE="URL" xlink:href="http://img.kb.dk/ma/musman/nyhartmann/fre7/fre70016.djvu"/>
      </m:file>
      <m:file ID="file:default:13:17">
        <m:FLocat LOCTYPE="URL" xlink:href="http://img.kb.dk/ma/musman/nyhartmann/fre7/fre70017.djvu"/>
      </m:file>
      <m:file ID="file:default:13:18">
        <m:FLocat LOCTYPE="URL" xlink:href="http://img.kb.dk/ma/musman/nyhartmann/fre7/fre70018.djvu"/>
      </m:file>
      <m:file ID="file:default:13:19">
        <m:FLocat LOCTYPE="URL" xlink:href="http://img.kb.dk/ma/musman/nyhartmann/fre7/fre70019.djvu"/>
      </m:file>
      <m:file ID="file:default:13:20">
        <m:FLocat LOCTYPE="URL" xlink:href="http://img.kb.dk/ma/musman/nyhartmann/fre7/fre70020.djvu"/>
      </m:file>
      <m:file ID="file:default:13:21">
        <m:FLocat LOCTYPE="URL" xlink:href="http://img.kb.dk/ma/musman/nyhartmann/fre7/fre70021.djvu"/>
      </m:file>
      <m:file ID="file:default:13:22">
        <m:FLocat LOCTYPE="URL" xlink:href="http://img.kb.dk/ma/musman/nyhartmann/fre7/fre70022.djvu"/>
      </m:file>
      <m:file ID="file:default:13:23">
        <m:FLocat LOCTYPE="URL" xlink:href="http://img.kb.dk/ma/musman/nyhartmann/fre7/fre70023.djvu"/>
      </m:file>
      <m:file ID="file:default:13:24">
        <m:FLocat LOCTYPE="URL" xlink:href="http://img.kb.dk/ma/musman/nyhartmann/fre7/fre70024.djvu"/>
      </m:file>
      <m:file ID="file:default:13:25">
        <m:FLocat LOCTYPE="URL" xlink:href="http://img.kb.dk/ma/musman/nyhartmann/fre7/fre70025.djvu"/>
      </m:file>
      <m:file ID="file:default:13:26">
        <m:FLocat LOCTYPE="URL" xlink:href="http://img.kb.dk/ma/musman/nyhartmann/fre7/fre70026.djvu"/>
      </m:file>
      <m:file ID="file:default:13:27">
        <m:FLocat LOCTYPE="URL" xlink:href="http://img.kb.dk/ma/musman/nyhartmann/fre7/fre70027.djvu"/>
      </m:file>
      <m:file ID="file:default:13:28">
        <m:FLocat LOCTYPE="URL" xlink:href="http://img.kb.dk/ma/musman/nyhartmann/fre7/fre70028.djvu"/>
      </m:file>
      <m:file ID="file:default:13:29">
        <m:FLocat LOCTYPE="URL" xlink:href="http://img.kb.dk/ma/musman/nyhartmann/fre7/fre70029.djvu"/>
      </m:file>
      <m:file ID="file:default:13:30">
        <m:FLocat LOCTYPE="URL" xlink:href="http://img.kb.dk/ma/musman/nyhartmann/fre7/fre70030.djvu"/>
      </m:file>
      <m:file ID="file:default:13:31">
        <m:FLocat LOCTYPE="URL" xlink:href="http://img.kb.dk/ma/musman/nyhartmann/fre7/fre70031.djvu"/>
      </m:file>
      <m:file ID="file:default:13:32">
        <m:FLocat LOCTYPE="URL" xlink:href="http://img.kb.dk/ma/musman/nyhartmann/fre7/fre70032.djvu"/>
      </m:file>
      <m:file ID="file:default:13:33">
        <m:FLocat LOCTYPE="URL" xlink:href="http://img.kb.dk/ma/musman/nyhartmann/fre7/fre70033.djvu"/>
      </m:file>
      <m:file ID="file:default:13:34">
        <m:FLocat LOCTYPE="URL" xlink:href="http://img.kb.dk/ma/musman/nyhartmann/fre7/fre70034.djvu"/>
      </m:file>
      <m:file ID="file:default:13:35">
        <m:FLocat LOCTYPE="URL" xlink:href="http://img.kb.dk/ma/musman/nyhartmann/fre7/fre70035.djvu"/>
      </m:file>
      <m:file ID="file:default:13:36">
        <m:FLocat LOCTYPE="URL" xlink:href="http://img.kb.dk/ma/musman/nyhartmann/fre7/fre70036.djvu"/>
      </m:file>
      <m:file ID="file:default:13:37">
        <m:FLocat LOCTYPE="URL" xlink:href="http://img.kb.dk/ma/musman/nyhartmann/fre7/fre70037.djvu"/>
      </m:file>
      <m:file ID="file:default:13:38">
        <m:FLocat LOCTYPE="URL" xlink:href="http://img.kb.dk/ma/musman/nyhartmann/fre7/fre70038.djvu"/>
      </m:file>
      <m:file ID="file:default:13:39">
        <m:FLocat LOCTYPE="URL" xlink:href="http://img.kb.dk/ma/musman/nyhartmann/fre7/fre70039.djvu"/>
      </m:file>
      <m:file ID="file:default:13:40">
        <m:FLocat LOCTYPE="URL" xlink:href="http://img.kb.dk/ma/musman/nyhartmann/fre7/fre70040.djvu"/>
      </m:file>
      <m:file ID="file:default:13:41">
        <m:FLocat LOCTYPE="URL" xlink:href="http://img.kb.dk/ma/musman/nyhartmann/fre7/fre70041.djvu"/>
      </m:file>
      <m:file ID="file:default:13:42">
        <m:FLocat LOCTYPE="URL" xlink:href="http://img.kb.dk/ma/musman/nyhartmann/fre7/fre70042.djvu"/>
      </m:file>
      <m:file ID="file:default:13:43">
        <m:FLocat LOCTYPE="URL" xlink:href="http://img.kb.dk/ma/musman/nyhartmann/fre7/fre70043.djvu"/>
      </m:file>
      <m:file ID="file:default:13:44">
        <m:FLocat LOCTYPE="URL" xlink:href="http://img.kb.dk/ma/musman/nyhartmann/fre7/fre70044.djvu"/>
      </m:file>
      <m:file ID="file:default:13:45">
        <m:FLocat LOCTYPE="URL" xlink:href="http://img.kb.dk/ma/musman/nyhartmann/fre7/fre70045.djvu"/>
      </m:file>
      <m:file ID="file:default:13:46">
        <m:FLocat LOCTYPE="URL" xlink:href="http://img.kb.dk/ma/musman/nyhartmann/fre7/fre70046.djvu"/>
      </m:file>
      <m:file ID="file:default:13:47">
        <m:FLocat LOCTYPE="URL" xlink:href="http://img.kb.dk/ma/musman/nyhartmann/fre7/fre70047.djvu"/>
      </m:file>
      <m:file ID="file:default:13:48">
        <m:FLocat LOCTYPE="URL" xlink:href="http://img.kb.dk/ma/musman/nyhartmann/fre7/fre70048.djvu"/>
      </m:file>
      <m:file ID="file:default:13:49">
        <m:FLocat LOCTYPE="URL" xlink:href="http://img.kb.dk/ma/musman/nyhartmann/fre7/fre70049.djvu"/>
      </m:file>
      <m:file ID="file:default:13:50">
        <m:FLocat LOCTYPE="URL" xlink:href="http://img.kb.dk/ma/musman/nyhartmann/fre7/fre70050.djvu"/>
      </m:file>
      <m:file ID="file:default:13:51">
        <m:FLocat LOCTYPE="URL" xlink:href="http://img.kb.dk/ma/musman/nyhartmann/fre7/fre70051.djvu"/>
      </m:file>
      <m:file ID="file:default:13:52">
        <m:FLocat LOCTYPE="URL" xlink:href="http://img.kb.dk/ma/musman/nyhartmann/fre7/fre70052.djvu"/>
      </m:file>
      <m:file ID="file:default:13:53">
        <m:FLocat LOCTYPE="URL" xlink:href="http://img.kb.dk/ma/musman/nyhartmann/fre7/fre70053.djvu"/>
      </m:file>
      <m:file ID="file:default:13:54">
        <m:FLocat LOCTYPE="URL" xlink:href="http://img.kb.dk/ma/musman/nyhartmann/fre7/fre70054.djvu"/>
      </m:file>
      <m:file ID="file:default:13:55">
        <m:FLocat LOCTYPE="URL" xlink:href="http://img.kb.dk/ma/musman/nyhartmann/fre7/fre70055.djvu"/>
      </m:file>
      <m:file ID="file:default:13:56">
        <m:FLocat LOCTYPE="URL" xlink:href="http://img.kb.dk/ma/musman/nyhartmann/fre7/fre70056.djvu"/>
      </m:file>
      <m:file ID="file:default:13:57">
        <m:FLocat LOCTYPE="URL" xlink:href="http://img.kb.dk/ma/musman/nyhartmann/fre7/fre70057.djvu"/>
      </m:file>
      <m:file ID="file:default:13:58">
        <m:FLocat LOCTYPE="URL" xlink:href="http://img.kb.dk/ma/musman/nyhartmann/fre7/fre70058.djvu"/>
      </m:file>
      <m:file ID="file:default:13:59">
        <m:FLocat LOCTYPE="URL" xlink:href="http://img.kb.dk/ma/musman/nyhartmann/fre7/fre70059.djvu"/>
      </m:file>
      <m:file ID="file:default:13:60">
        <m:FLocat LOCTYPE="URL" xlink:href="http://img.kb.dk/ma/musman/nyhartmann/fre7/fre70060.djvu"/>
      </m:file>
      <m:file ID="file:default:13:61">
        <m:FLocat LOCTYPE="URL" xlink:href="http://img.kb.dk/ma/musman/nyhartmann/fre7/fre70061.djvu"/>
      </m:file>
      <m:file ID="file:default:13:62">
        <m:FLocat LOCTYPE="URL" xlink:href="http://img.kb.dk/ma/musman/nyhartmann/fre7/fre70062.djvu"/>
      </m:file>
      <m:file ID="file:default:13:63">
        <m:FLocat LOCTYPE="URL" xlink:href="http://img.kb.dk/ma/musman/nyhartmann/fre7/fre70063.djvu"/>
      </m:file>
      <m:file ID="file:default:13:64">
        <m:FLocat LOCTYPE="URL" xlink:href="http://img.kb.dk/ma/musman/nyhartmann/fre7/fre70064.djvu"/>
      </m:file>
      <m:file ID="file:default:13:65">
        <m:FLocat LOCTYPE="URL" xlink:href="http://img.kb.dk/ma/musman/nyhartmann/fre7/fre70065.djvu"/>
      </m:file>
      <m:file ID="file:default:13:66">
        <m:FLocat LOCTYPE="URL" xlink:href="http://img.kb.dk/ma/musman/nyhartmann/fre7/fre70066.djvu"/>
      </m:file>
      <m:file ID="file:default:13:67">
        <m:FLocat LOCTYPE="URL" xlink:href="http://img.kb.dk/ma/musman/nyhartmann/fre7/fre70067.djvu"/>
      </m:file>
      <m:file ID="file:default:13:68">
        <m:FLocat LOCTYPE="URL" xlink:href="http://img.kb.dk/ma/musman/nyhartmann/fre7/fre70068.djvu"/>
      </m:file>
      <m:file ID="file:default:13:69">
        <m:FLocat LOCTYPE="URL" xlink:href="http://img.kb.dk/ma/musman/nyhartmann/fre7/fre70069.djvu"/>
      </m:file>
      <m:file ID="file:default:13:70">
        <m:FLocat LOCTYPE="URL" xlink:href="http://img.kb.dk/ma/musman/nyhartmann/fre7/fre70070.djvu"/>
      </m:file>
      <m:file ID="file:default:13:71">
        <m:FLocat LOCTYPE="URL" xlink:href="http://img.kb.dk/ma/musman/nyhartmann/fre7/fre70071.djvu"/>
      </m:file>
      <m:file ID="file:default:13:72">
        <m:FLocat LOCTYPE="URL" xlink:href="http://img.kb.dk/ma/musman/nyhartmann/fre7/fre70072.djvu"/>
      </m:file>
      <m:file ID="file:default:13:73">
        <m:FLocat LOCTYPE="URL" xlink:href="http://img.kb.dk/ma/musman/nyhartmann/fre7/fre70073.djvu"/>
      </m:file>
      <m:file ID="file:default:13:74">
        <m:FLocat LOCTYPE="URL" xlink:href="http://img.kb.dk/ma/musman/nyhartmann/fre7/fre70074.djvu"/>
      </m:file>
      <m:file ID="file:default:13:75">
        <m:FLocat LOCTYPE="URL" xlink:href="http://img.kb.dk/ma/musman/nyhartmann/fre7/fre70075.djvu"/>
      </m:file>
      <m:file ID="file:default:13:76">
        <m:FLocat LOCTYPE="URL" xlink:href="http://img.kb.dk/ma/musman/nyhartmann/fre7/fre70076.djvu"/>
      </m:file>
      <m:file ID="file:default:13:77">
        <m:FLocat LOCTYPE="URL" xlink:href="http://img.kb.dk/ma/musman/nyhartmann/fre7/fre70077.djvu"/>
      </m:file>
      <m:file ID="file:default:13:78">
        <m:FLocat LOCTYPE="URL" xlink:href="http://img.kb.dk/ma/musman/nyhartmann/fre7/fre70078.djvu"/>
      </m:file>
      <m:file ID="file:default:13:79">
        <m:FLocat LOCTYPE="URL" xlink:href="http://img.kb.dk/ma/musman/nyhartmann/fre7/fre70079.djvu"/>
      </m:file>
      <m:file ID="file:default:13:80">
        <m:FLocat LOCTYPE="URL" xlink:href="http://img.kb.dk/ma/musman/nyhartmann/fre7/fre70080.djvu"/>
      </m:file>
    </m:fileGrp>
  </m:fileSec>
  <m:structMap type="physical">
    <m:div ID="struct-root" DMDID="md-root">
      <m:div ID="div:default:13:0" xml:lang="dan" ORDERLABEL="0" LABEL="Nr. 1 Chor.  O, Sorgens Syn!">
        <m:fptr FILEID="file:default:13:0"/>
      </m:div>
      <m:div ID="div:default:13:1" xml:lang="dan" ORDERLABEL="1">
        <m:fptr FILEID="file:default:13:1"/>
      </m:div>
      <m:div ID="div:default:13:2" xml:lang="dan" ORDERLABEL="2">
        <m:fptr FILEID="file:default:13:2"/>
      </m:div>
      <m:div ID="div:default:13:3" xml:lang="dan" ORDERLABEL="3">
        <m:fptr FILEID="file:default:13:3"/>
      </m:div>
      <m:div ID="div:default:13:4" xml:lang="dan" ORDERLABEL="4">
        <m:fptr FILEID="file:default:13:4"/>
      </m:div>
      <m:div ID="div:default:13:5" xml:lang="dan" ORDERLABEL="5">
        <m:fptr FILEID="file:default:13:5"/>
      </m:div>
      <m:div ID="div:default:13:6" xml:lang="dan" ORDERLABEL="6">
        <m:fptr FILEID="file:default:13:6"/>
      </m:div>
      <m:div ID="div:default:13:7" xml:lang="dan" ORDERLABEL="7">
        <m:fptr FILEID="file:default:13:7"/>
      </m:div>
      <m:div ID="div:default:13:8" xml:lang="dan" ORDERLABEL="8">
        <m:fptr FILEID="file:default:13:8"/>
      </m:div>
      <m:div ID="div:default:13:9" xml:lang="dan" ORDERLABEL="9">
        <m:fptr FILEID="file:default:13:9"/>
      </m:div>
      <m:div ID="div:default:13:10" xml:lang="dan" ORDERLABEL="10">
        <m:fptr FILEID="file:default:13:10"/>
      </m:div>
      <m:div ID="div:default:13:11" xml:lang="dan" ORDERLABEL="11">
        <m:fptr FILEID="file:default:13:11"/>
      </m:div>
      <m:div ID="div:default:13:12" xml:lang="dan" ORDERLABEL="12" LABEL="Nr. 2 Sang.  Ja, aand kun tungt ">
        <m:fptr FILEID="file:default:13:12"/>
      </m:div>
      <m:div ID="div:default:13:13" xml:lang="dan" ORDERLABEL="13">
        <m:fptr FILEID="file:default:13:13"/>
      </m:div>
      <m:div ID="div:default:13:14" xml:lang="dan" ORDERLABEL="14">
        <m:fptr FILEID="file:default:13:14"/>
      </m:div>
      <m:div ID="div:default:13:15" xml:lang="dan" ORDERLABEL="15">
        <m:fptr FILEID="file:default:13:15"/>
      </m:div>
      <m:div ID="div:default:13:16" xml:lang="dan" ORDERLABEL="16">
        <m:fptr FILEID="file:default:13:16"/>
      </m:div>
      <m:div ID="div:default:13:17" xml:lang="dan" ORDERLABEL="17">
        <m:fptr FILEID="file:default:13:17"/>
      </m:div>
      <m:div ID="div:default:13:18" xml:lang="dan" ORDERLABEL="18" LABEL="Nr. 3 Recitativ og Chor. Hvad var hans Lod?">
        <m:fptr FILEID="file:default:13:18"/>
      </m:div>
      <m:div ID="div:default:13:19" xml:lang="dan" ORDERLABEL="19">
        <m:fptr FILEID="file:default:13:19"/>
      </m:div>
      <m:div ID="div:default:13:20" xml:lang="dan" ORDERLABEL="20">
        <m:fptr FILEID="file:default:13:20"/>
      </m:div>
      <m:div ID="div:default:13:21" xml:lang="dan" ORDERLABEL="21">
        <m:fptr FILEID="file:default:13:21"/>
      </m:div>
      <m:div ID="div:default:13:22" xml:lang="dan" ORDERLABEL="22">
        <m:fptr FILEID="file:default:13:22"/>
      </m:div>
      <m:div ID="div:default:13:23" xml:lang="dan" ORDERLABEL="23">
        <m:fptr FILEID="file:default:13:23"/>
      </m:div>
      <m:div ID="div:default:13:24" xml:lang="dan" ORDERLABEL="24">
        <m:fptr FILEID="file:default:13:24"/>
      </m:div>
      <m:div ID="div:default:13:25" xml:lang="dan" ORDERLABEL="25">
        <m:fptr FILEID="file:default:13:25"/>
      </m:div>
      <m:div ID="div:default:13:26" xml:lang="dan" ORDERLABEL="26">
        <m:fptr FILEID="file:default:13:26"/>
      </m:div>
      <m:div ID="div:default:13:27" xml:lang="dan" ORDERLABEL="27">
        <m:fptr FILEID="file:default:13:27"/>
      </m:div>
      <m:div ID="div:default:13:28" xml:lang="dan" ORDERLABEL="28" LABEL="Nr. 4 Qvartet. Herlige Tid">
        <m:fptr FILEID="file:default:13:28"/>
      </m:div>
      <m:div ID="div:default:13:29" xml:lang="dan" ORDERLABEL="29">
        <m:fptr FILEID="file:default:13:29"/>
      </m:div>
      <m:div ID="div:default:13:30" xml:lang="dan" ORDERLABEL="30">
        <m:fptr FILEID="file:default:13:30"/>
      </m:div>
      <m:div ID="div:default:13:31" xml:lang="dan" ORDERLABEL="31">
        <m:fptr FILEID="file:default:13:31"/>
      </m:div>
      <m:div ID="div:default:13:32" xml:lang="dan" ORDERLABEL="32">
        <m:fptr FILEID="file:default:13:32"/>
      </m:div>
      <m:div ID="div:default:13:33" xml:lang="dan" ORDERLABEL="33">
        <m:fptr FILEID="file:default:13:33"/>
      </m:div>
      <m:div ID="div:default:13:34" xml:lang="dan" ORDERLABEL="34">
        <m:fptr FILEID="file:default:13:34"/>
      </m:div>
      <m:div ID="div:default:13:35" xml:lang="dan" ORDERLABEL="35">
        <m:fptr FILEID="file:default:13:35"/>
      </m:div>
      <m:div ID="div:default:13:36" xml:lang="dan" ORDERLABEL="36">
        <m:fptr FILEID="file:default:13:36"/>
      </m:div>
      <m:div ID="div:default:13:37" xml:lang="dan" ORDERLABEL="37">
        <m:fptr FILEID="file:default:13:37"/>
      </m:div>
      <m:div ID="div:default:13:38" xml:lang="dan" ORDERLABEL="38">
        <m:fptr FILEID="file:default:13:38"/>
      </m:div>
      <m:div ID="div:default:13:39" xml:lang="dan" ORDERLABEL="39" LABEL="Nr. 5 Sang med Chor-Omqvæd. Studenten lagde bort">
        <m:fptr FILEID="file:default:13:39"/>
      </m:div>
      <m:div ID="div:default:13:40" xml:lang="dan" ORDERLABEL="40">
        <m:fptr FILEID="file:default:13:40"/>
      </m:div>
      <m:div ID="div:default:13:41" xml:lang="dan" ORDERLABEL="41">
        <m:fptr FILEID="file:default:13:41"/>
      </m:div>
      <m:div ID="div:default:13:42" xml:lang="dan" ORDERLABEL="42">
        <m:fptr FILEID="file:default:13:42"/>
      </m:div>
      <m:div ID="div:default:13:43" xml:lang="dan" ORDERLABEL="43">
        <m:fptr FILEID="file:default:13:43"/>
      </m:div>
      <m:div ID="div:default:13:44" xml:lang="dan" ORDERLABEL="44">
        <m:fptr FILEID="file:default:13:44"/>
      </m:div>
      <m:div ID="div:default:13:45" xml:lang="dan" ORDERLABEL="45" LABEL="Nr. 6 Qvartet og Chor. Saa sving i Seiersklædebon">
        <m:fptr FILEID="file:default:13:45"/>
      </m:div>
      <m:div ID="div:default:13:46" xml:lang="dan" ORDERLABEL="46">
        <m:fptr FILEID="file:default:13:46"/>
      </m:div>
      <m:div ID="div:default:13:47" xml:lang="dan" ORDERLABEL="47">
        <m:fptr FILEID="file:default:13:47"/>
      </m:div>
      <m:div ID="div:default:13:48" xml:lang="dan" ORDERLABEL="48">
        <m:fptr FILEID="file:default:13:48"/>
      </m:div>
      <m:div ID="div:default:13:49" xml:lang="dan" ORDERLABEL="49">
        <m:fptr FILEID="file:default:13:49"/>
      </m:div>
      <m:div ID="div:default:13:50" xml:lang="dan" ORDERLABEL="50">
        <m:fptr FILEID="file:default:13:50"/>
      </m:div>
      <m:div ID="div:default:13:51" xml:lang="dan" ORDERLABEL="51">
        <m:fptr FILEID="file:default:13:51"/>
      </m:div>
      <m:div ID="div:default:13:52" xml:lang="dan" ORDERLABEL="52">
        <m:fptr FILEID="file:default:13:52"/>
      </m:div>
      <m:div ID="div:default:13:53" xml:lang="dan" ORDERLABEL="53">
        <m:fptr FILEID="file:default:13:53"/>
      </m:div>
      <m:div ID="div:default:13:54" xml:lang="dan" ORDERLABEL="54">
        <m:fptr FILEID="file:default:13:54"/>
      </m:div>
      <m:div ID="div:default:13:55" xml:lang="dan" ORDERLABEL="55">
        <m:fptr FILEID="file:default:13:55"/>
      </m:div>
      <m:div ID="div:default:13:56" xml:lang="dan" ORDERLABEL="56" LABEL="Nr. 7 Choral. Hvad er Jordens Kongekroner">
        <m:fptr FILEID="file:default:13:56"/>
      </m:div>
      <m:div ID="div:default:13:57" xml:lang="dan" ORDERLABEL="57">
        <m:fptr FILEID="file:default:13:57"/>
      </m:div>
      <m:div ID="div:default:13:58" xml:lang="dan" ORDERLABEL="58">
        <m:fptr FILEID="file:default:13:58"/>
      </m:div>
      <m:div ID="div:default:13:59" xml:lang="dan" ORDERLABEL="59">
        <m:fptr FILEID="file:default:13:59"/>
      </m:div>
      <m:div ID="div:default:13:60" xml:lang="dan" ORDERLABEL="60">
        <m:fptr FILEID="file:default:13:60"/>
      </m:div>
      <m:div ID="div:default:13:61" xml:lang="dan" ORDERLABEL="61">
        <m:fptr FILEID="file:default:13:61"/>
      </m:div>
      <m:div ID="div:default:13:62" xml:lang="dan" ORDERLABEL="62">
        <m:fptr FILEID="file:default:13:62"/>
      </m:div>
      <m:div ID="div:default:13:63" xml:lang="dan" ORDERLABEL="63">
        <m:fptr FILEID="file:default:13:63"/>
      </m:div>
      <m:div ID="div:default:13:64" xml:lang="dan" ORDERLABEL="64" LABEL="Nr. 8 Slutningschor. Kongernes Konge">
        <m:fptr FILEID="file:default:13:64"/>
      </m:div>
      <m:div ID="div:default:13:65" xml:lang="dan" ORDERLABEL="65">
        <m:fptr FILEID="file:default:13:65"/>
      </m:div>
      <m:div ID="div:default:13:66" xml:lang="dan" ORDERLABEL="66">
        <m:fptr FILEID="file:default:13:66"/>
      </m:div>
      <m:div ID="div:default:13:67" xml:lang="dan" ORDERLABEL="67">
        <m:fptr FILEID="file:default:13:67"/>
      </m:div>
      <m:div ID="div:default:13:68" xml:lang="dan" ORDERLABEL="68">
        <m:fptr FILEID="file:default:13:68"/>
      </m:div>
      <m:div ID="div:default:13:69" xml:lang="dan" ORDERLABEL="69">
        <m:fptr FILEID="file:default:13:69"/>
      </m:div>
      <m:div ID="div:default:13:70" xml:lang="dan" ORDERLABEL="70">
        <m:fptr FILEID="file:default:13:70"/>
      </m:div>
      <m:div ID="div:default:13:71" xml:lang="dan" ORDERLABEL="71">
        <m:fptr FILEID="file:default:13:71"/>
      </m:div>
      <m:div ID="div:default:13:72" xml:lang="dan" ORDERLABEL="72">
        <m:fptr FILEID="file:default:13:72"/>
      </m:div>
      <m:div ID="div:default:13:73" xml:lang="dan" ORDERLABEL="73">
        <m:fptr FILEID="file:default:13:73"/>
      </m:div>
      <m:div ID="div:default:13:74" xml:lang="dan" ORDERLABEL="74">
        <m:fptr FILEID="file:default:13:74"/>
      </m:div>
      <m:div ID="div:default:13:75" xml:lang="dan" ORDERLABEL="75">
        <m:fptr FILEID="file:default:13:75"/>
      </m:div>
      <m:div ID="div:default:13:76" xml:lang="dan" ORDERLABEL="76">
        <m:fptr FILEID="file:default:13:76"/>
      </m:div>
      <m:div ID="div:default:13:77" xml:lang="dan" ORDERLABEL="77">
        <m:fptr FILEID="file:default:13:77"/>
      </m:div>
      <m:div ID="div:default:13:78" xml:lang="dan" ORDERLABEL="78">
        <m:fptr FILEID="file:default:13:78"/>
      </m:div>
      <m:div ID="div:default:13:79" xml:lang="dan" ORDERLABEL="79">
        <m:fptr FILEID="file:default:13:79"/>
      </m:div>
      <m:div ID="div:default:13:80" xml:lang="dan" ORDERLABEL="80">
        <m:fptr FILEID="file:default:13:80"/>
      </m:div>
    </m:div>
  </m:structMap>
</m:mets>
